{"servers":[{"host":"localhost","port":"8080","name":"Local Server","listing":{"motd":"Just another Pokemon TCG server","name":"Wykerd's Server"}},{"host":"localhost","port":"8080","name":"Local Server","listing":{"motd":"Just another Pokemon TCG server","name":"Wykerd's Server"}},{"host":"localhost","port":"8080","name":"Local Server","listing":{"motd":"Why don't you join now?","name":"Epic Gamer Server"}},{"host":"localhost","port":"8080","name":"Local Server","listing":{"motd":"Why don't you join now?","name":"Epic Gamer Server"}},{"host":"localhost","port":"8080","name":"Local Server","listing":{"motd":"Why don't you join now?","name":"Epic Gamer Server"}},{"host":"localhost","port":"8080","name":"Local Server","listing":{"motd":"Just another Pokemon TCG server","name":"Wykerd's Server"}}]}
